{
    "teams": [
        {
            "id": 9999,
            "teamId": "DEMOTEAM",
            "name": "DEMO TEAM",
            "memo": "THIS IS DEMO TEAM.\nTHANK YOU FOR TRYING OUT THE DEMO MODE.",
            "adminUserId": 9997,
            "private": false,
            "isPaidTeam": true,
            "teamMember": [
                {
                    "id":9997,
                    "initials":"TE",
                    "name":"TESTUSER",
                    "email":"TEST",
                    "color":"red",
                    "simpleIcon":true,
                    "bgImg":"",
                    "iconImg":{"url": ""},
                    "message":"THIS IS TEST USER.\nTHANK YOU FOR DEMO MODE TRIAL.",
                    "trialed":false
                },
                {
                    "id":9998,
                    "initials":"パ",
                    "name":"Mr.パンダ",
                    "email":"パンダの国五丁目四番",
                    "color":"red",
                    "simpleIcon":false,
                    "bgImg":"",
                    "iconImg":{"url": ""},
                    "message":"パンダを選んでくれてありがとう！\n製品版でも、アイコン画像を一度もアップロードしていない時だけは僕に会えるよ！\n",
                    "trialed":false
                },
                {
                    "id":9999,
                    "initials":"MO",
                    "name":"Monster",
                    "email":"monster",
                    "color":"red",
                    "simpleIcon":false,
                    "bgImg":"",
                    "iconImg":{"url": "https://itamaster.s3.amazonaws.com/uploads/user/iconImg/4/chmigndystxrbljpv.png"},
                    "message":"GYAAAAAAAAAAAAA!!!!",
                    "trialed":false
                }
            ],
            "invitations":[]
        }
    ],
    "projects": [
        {
            "id": 9999,
            "name": "DEMO PROJECT",
            "memo": "THIS IS DEMO PROJECT.\nTHANK YOU FOR TRYING OUT THE DEMO MODE.",
            "createEnvironmentSteps": false,
            "testEnvironmentURL": "https://www.google.com/",
            "repositoryURL": "https://github.co.jp/",
            "enabled": true,
            "gitCooperation": false,
            "team_id": 9999,
            "created_at": "2021-10-03T18:09:36.693+09:00",
            "updated_at": "2021-10-03T18:09:36.693+09:00"
        }
    ],
    "testsuits": [
        {
            "id": 9991,
            "title": "TESTSUITE DEMO 01",
            "remarks": "DEMO",
            "steps": 1200,
            "sequential_id": 1,
            "creatorId": 9997,
            "team_id": 9999,
            "project_id": 9999,
            "created_at": "2021-10-03T18:09:51.908+09:00",
            "updated_at": "2021-10-12T22:51:40.393+09:00",
            "writers": [
                9998,
                9999
            ]
        },
        {
            "id": 9992,
            "title": "TESTSUITE DEMO 02",
            "remarks": "DEMO",
            "steps": 6000,
            "sequential_id": 2,
            "creatorId": 9997,
            "team_id": 9999,
            "project_id": 9999,
            "created_at": "2021-10-03T18:10:06.220+09:00",
            "updated_at": "2021-10-12T22:52:08.127+09:00",
            "writers": [
                9997
            ]
        },
        {
            "id": 9993,
            "title": "TESTSUITE DEMO 03",
            "remarks": "DEMO",
            "steps": 200,
            "sequential_id": 3,
            "creatorId": 9997,
            "team_id": 9999,
            "project_id": 9999,
            "created_at": "2021-10-03T18:10:24.597+09:00",
            "updated_at": "2021-10-12T22:51:54.178+09:00",
            "writers": [
                9997
            ]
        },
        {
            "id": 9994,
            "title": "TESTSUITE DEMO 04",
            "remarks": "DEMO",
            "steps": 500,
            "sequential_id": 4,
            "creatorId": 9997,
            "team_id": 9999,
            "project_id": 9999,
            "created_at": "2021-10-12T22:52:23.550+09:00",
            "updated_at": "2021-10-12T22:52:23.550+09:00",
            "writers": []
        },
        {
            "id": 9995,
            "title": "TESTSUITE DEMO 05",
            "remarks": "DEMO",
            "steps": 300,
            "sequential_id": 5,
            "creatorId": 9997,
            "team_id": 9999,
            "project_id": 9999,
            "created_at": "2021-10-12T22:52:35.973+09:00",
            "updated_at": "2021-10-12T22:52:44.454+09:00",
            "writers": []
        },
        {
            "id": 9996,
            "title": "TESTSUITE DEMO 06",
            "remarks": "DEMO",
            "steps": 20,
            "sequential_id": 6,
            "creatorId": 9997,
            "team_id": 9999,
            "project_id": 9999,
            "created_at": "2021-10-12T22:52:55.076+09:00",
            "updated_at": "2021-10-12T22:52:55.076+09:00",
            "writers": []
        },
        {
            "id": 9997,
            "title": "TESTSUITE DEMO 07",
            "remarks": "DEMO",
            "steps": 3600,
            "sequential_id": 7,
            "creatorId": 9997,
            "team_id": 9999,
            "project_id": 9999,
            "created_at": "2021-10-12T22:53:07.417+09:00",
            "updated_at": "2021-10-12T22:53:07.417+09:00",
            "writers": []
        },
        {
            "id": 9998,
            "title": "TESTSUITE DEMO 08",
            "remarks": "DEMO",
            "steps": 0,
            "sequential_id": 8,
            "creatorId": 9997,
            "team_id": 9999,
            "project_id": 9999,
            "created_at": "2021-10-12T22:53:19.717+09:00",
            "updated_at": "2021-10-12T22:53:19.717+09:00",
            "writers": [
                9998
            ]
        },
        {
            "id": 9999,
            "title": "TESTSUITE DEMO 09",
            "remarks": "DEMO",
            "steps": 800,
            "sequential_id": 9,
            "creatorId": 9997,
            "team_id": 9999,
            "project_id": 9999,
            "created_at": "2021-10-12T22:53:32.382+09:00",
            "updated_at": "2021-10-12T22:53:32.382+09:00",
            "writers": []
        },
        {
            "id": 10000,
            "title": "TESTSUITE DEMO 10",
            "remarks": "DEMO",
            "steps": 3060,
            "sequential_id": 10,
            "creatorId": 9997,
            "team_id": 9999,
            "project_id": 9999,
            "created_at": "2021-10-12T22:53:44.875+09:00",
            "updated_at": "2021-10-12T22:53:44.875+09:00",
            "writers": []
        }
    ],
    "testcases": [
        {
            "id": 1,
            "title": "DEMO TESTCASE 01",
            "order": 1,
            "sequential_id": 1,
            "status": "complete",
            "creatorId": 9997,
            "testerId": 9997,
            "lastEditorId": 9997,
            "importance": 1,
            "lock": false,
            "team_id": 9999,
            "project_id": 9999,
            "testsuite_id": 9991,
            "created_at": "2021-10-03T18:10:38.226+09:00",
            "updated_at": "2021-10-12T23:59:28.656+09:00",
            "testLogs": [
                {
                    "id": 8,
                    "sequential_id": 1,
                    "testerId": 9997,
                    "beforeStatus": "notRunning",
                    "afterStatus": "complete",
                    "reason": "",
                    "team_id": 9999,
                    "project_id": 9999,
                    "testsuite_id": 9991,
                    "testcase_id": 1,
                    "created_at": "2021-10-12T23:59:28.673+09:00",
                    "updated_at": "2021-10-12T23:59:28.673+09:00"
                },
                {
                    "id": 9998,
                    "sequential_id": 2,
                    "testerId": 9998,
                    "beforeStatus": "complete",
                    "afterStatus": "issue",
                    "reason": "",
                    "team_id": 9999,
                    "project_id": 9999,
                    "testsuite_id": 9991,
                    "testcase_id": 1,
                    "created_at": "2021-10-13T23:59:28.673+09:00",
                    "updated_at": "2021-10-12T23:59:28.673+09:00"
                },
                {
                    "id": 9999,
                    "sequential_id": 3,
                    "testerId": 9997,
                    "beforeStatus": "issue",
                    "afterStatus": "complete",
                    "reason": "This is mock data. Remarks can be added when the test is executed.",
                    "team_id": 9999,
                    "project_id": 9999,
                    "testsuite_id": 9991,
                    "testcase_id": 1,
                    "created_at": "2021-10-14T23:59:28.673+09:00",
                    "updated_at": "2021-10-12T23:59:28.673+09:00"
                }
            ],
            "prerequisites": [
                {
                    "id": 18,
                    "sequential_id": 1,
                    "contents": "PREREQUISITES 01",
                    "team_id": 9999,
                    "project_id": 9999,
                    "testsuite_id": 9991,
                    "testcase_id": 1,
                    "created_at": "2021-10-12T23:56:11.763+09:00",
                    "updated_at": "2021-10-12T23:56:11.763+09:00"
                },
                {
                    "id": 19,
                    "sequential_id": 2,
                    "contents": "PREREQUISITES 02",
                    "team_id": 9999,
                    "project_id": 9999,
                    "testsuite_id": 9991,
                    "testcase_id": 1,
                    "created_at": "2021-10-12T23:56:11.780+09:00",
                    "updated_at": "2021-10-12T23:56:11.780+09:00"
                },
                {
                    "id": 20,
                    "sequential_id": 3,
                    "contents": "PREREQUISITES 03",
                    "team_id": 9999,
                    "project_id": 9999,
                    "testsuite_id": 9991,
                    "testcase_id": 1,
                    "created_at": "2021-10-12T23:56:11.796+09:00",
                    "updated_at": "2021-10-12T23:56:11.796+09:00"
                }
            ],
            "process": [
                {
                    "id": 5,
                    "sequential_id": 1,
                    "contents": "PROCESS 01",
                    "team_id": 9999,
                    "project_id": 9999,
                    "testsuite_id": 9991,
                    "testcase_id": 1,
                    "created_at": "2021-10-12T23:56:11.819+09:00",
                    "updated_at": "2021-10-12T23:56:11.819+09:00"
                },
                {
                    "id": 6,
                    "sequential_id": 2,
                    "contents": "PROCESS 02",
                    "team_id": 9999,
                    "project_id": 9999,
                    "testsuite_id": 9991,
                    "testcase_id": 1,
                    "created_at": "2021-10-12T23:56:11.835+09:00",
                    "updated_at": "2021-10-12T23:56:11.835+09:00"
                },
                {
                    "id": 7,
                    "sequential_id": 3,
                    "contents": "PROCESS 03",
                    "team_id": 9999,
                    "project_id": 9999,
                    "testsuite_id": 9991,
                    "testcase_id": 1,
                    "created_at": "2021-10-12T23:56:11.852+09:00",
                    "updated_at": "2021-10-12T23:56:11.852+09:00"
                }
            ],
            "expect": [
                {
                    "id": 6,
                    "sequential_id": 1,
                    "contents": "EXPECT 01",
                    "team_id": 9999,
                    "project_id": 9999,
                    "testsuite_id": 9991,
                    "testcase_id": 1,
                    "created_at": "2021-10-12T23:56:11.875+09:00",
                    "updated_at": "2021-10-12T23:56:11.875+09:00"
                },
                {
                    "id": 7,
                    "sequential_id": 2,
                    "contents": "EXPECT 02",
                    "team_id": 9999,
                    "project_id": 9999,
                    "testsuite_id": 9991,
                    "testcase_id": 1,
                    "created_at": "2021-10-12T23:56:11.891+09:00",
                    "updated_at": "2021-10-12T23:56:11.891+09:00"
                },
                {
                    "id": 8,
                    "sequential_id": 3,
                    "contents": "EXPECT 03",
                    "team_id": 9999,
                    "project_id": 9999,
                    "testsuite_id": 9991,
                    "testcase_id": 1,
                    "created_at": "2021-10-12T23:56:11.907+09:00",
                    "updated_at": "2021-10-12T23:56:11.907+09:00"
                }
            ]
        },
        {
            "id": 2,
            "title": "DEMO TESTCASE 02",
            "order": 2,
            "sequential_id": 2,
            "status": "complete",
            "creatorId": 9997,
            "testerId": 9997,
            "lastEditorId": 9997,
            "importance": 2,
            "lock": false,
            "team_id": 9999,
            "project_id": 9999,
            "testsuite_id": 9991,
            "created_at": "2021-10-03T18:10:47.278+09:00",
            "updated_at": "2021-10-12T23:59:28.701+09:00",
            "testLogs": [
                {
                    "id": 1,
                    "sequential_id": 1,
                    "testerId": 9997,
                    "beforeStatus": "notRunning",
                    "afterStatus": "complete",
                    "reason": "",
                    "team_id": 9999,
                    "project_id": 9999,
                    "testsuite_id": 9991,
                    "testcase_id": 2,
                    "created_at": "2021-10-03T18:40:33.800+09:00",
                    "updated_at": "2021-10-03T18:40:33.800+09:00"
                },
                {
                    "id": 6,
                    "sequential_id": 2,
                    "testerId": 9997,
                    "beforeStatus": "complete",
                    "afterStatus": "retest",
                    "reason": "再テストに変更",
                    "team_id": 9999,
                    "project_id": 9999,
                    "testsuite_id": 9991,
                    "testcase_id": 2,
                    "created_at": "2021-10-04T13:00:17.674+09:00",
                    "updated_at": "2021-10-04T13:00:17.674+09:00"
                },
                {
                    "id": 9,
                    "sequential_id": 3,
                    "testerId": 9997,
                    "beforeStatus": "retest",
                    "afterStatus": "complete",
                    "reason": "",
                    "team_id": 9999,
                    "project_id": 9999,
                    "testsuite_id": 9991,
                    "testcase_id": 2,
                    "created_at": "2021-10-12T23:59:28.718+09:00",
                    "updated_at": "2021-10-12T23:59:28.718+09:00"
                }
            ],
            "prerequisites": [],
            "process": [],
            "expect": []
        },
        {
            "id": 3,
            "title": "DEMO TESTCASE 03",
            "order": 3,
            "sequential_id": 3,
            "status": "issue",
            "creatorId": 9997,
            "testerId": 9997,
            "lastEditorId": 9997,
            "importance": 3,
            "lock": false,
            "team_id": 9999,
            "project_id": 9999,
            "testsuite_id": 9991,
            "created_at": "2021-10-03T18:10:54.597+09:00",
            "updated_at": "2021-10-12T23:59:28.743+09:00",
            "testLogs": [
                {
                    "id": 2,
                    "sequential_id": 1,
                    "testerId": 9997,
                    "beforeStatus": "notRunning",
                    "afterStatus": "complete",
                    "reason": "",
                    "team_id": 9999,
                    "project_id": 9999,
                    "testsuite_id": 9991,
                    "testcase_id": 3,
                    "created_at": "2021-10-03T18:40:33.843+09:00",
                    "updated_at": "2021-10-03T18:40:33.843+09:00"
                },
                {
                    "id": 4,
                    "sequential_id": 2,
                    "testerId": 9997,
                    "beforeStatus": "complete",
                    "afterStatus": "retest",
                    "reason": "",
                    "team_id": 9999,
                    "project_id": 9999,
                    "testsuite_id": 9991,
                    "testcase_id": 3,
                    "created_at": "2021-10-03T22:49:43.816+09:00",
                    "updated_at": "2021-10-03T22:49:43.816+09:00"
                },
                {
                    "id": 10,
                    "sequential_id": 3,
                    "testerId": 9997,
                    "beforeStatus": "retest",
                    "afterStatus": "issue",
                    "reason": "ISSUE DEMO",
                    "team_id": 9999,
                    "project_id": 9999,
                    "testsuite_id": 9991,
                    "testcase_id": 3,
                    "created_at": "2021-10-12T23:59:28.759+09:00",
                    "updated_at": "2021-10-12T23:59:28.759+09:00"
                }
            ],
            "prerequisites": [
                {
                    "id": 21,
                    "sequential_id": 1,
                    "contents": "PREREQUISITES ",
                    "team_id": 9999,
                    "project_id": 9999,
                    "testsuite_id": 9991,
                    "testcase_id": 3,
                    "created_at": "2021-10-12T23:56:59.821+09:00",
                    "updated_at": "2021-10-12T23:56:59.821+09:00"
                }
            ],
            "process": [
                {
                    "id": 8,
                    "sequential_id": 1,
                    "contents": "",
                    "team_id": 9999,
                    "project_id": 9999,
                    "testsuite_id": 9991,
                    "testcase_id": 3,
                    "created_at": "2021-10-12T23:56:59.843+09:00",
                    "updated_at": "2021-10-12T23:56:59.843+09:00"
                }
            ],
            "expect": [
                {
                    "id": 9,
                    "sequential_id": 1,
                    "contents": "EXPECT",
                    "team_id": 9999,
                    "project_id": 9999,
                    "testsuite_id": 9991,
                    "testcase_id": 3,
                    "created_at": "2021-10-12T23:56:59.863+09:00",
                    "updated_at": "2021-10-12T23:56:59.863+09:00"
                }
            ]
        },
        {
            "id": 4,
            "title": "DEMO TESTCASE 04",
            "order": 4,
            "sequential_id": 4,
            "status": "complete",
            "creatorId": 9997,
            "testerId": 9997,
            "lastEditorId": 9997,
            "importance": 1,
            "lock": false,
            "team_id": 9999,
            "project_id": 9999,
            "testsuite_id": 9991,
            "created_at": "2021-10-03T18:11:00.753+09:00",
            "updated_at": "2021-10-12T23:57:48.480+09:00",
            "testLogs": [
                {
                    "id": 3,
                    "sequential_id": 1,
                    "testerId": 9997,
                    "beforeStatus": "notRunning",
                    "afterStatus": "issue",
                    "reason": "",
                    "team_id": 9999,
                    "project_id": 9999,
                    "testsuite_id": 9991,
                    "testcase_id": 4,
                    "created_at": "2021-10-03T18:40:33.886+09:00",
                    "updated_at": "2021-10-03T18:40:33.886+09:00"
                },
                {
                    "id": 5,
                    "sequential_id": 2,
                    "testerId": 9997,
                    "beforeStatus": "issue",
                    "afterStatus": "issue",
                    "reason": "",
                    "team_id": 9999,
                    "project_id": 9999,
                    "testsuite_id": 9991,
                    "testcase_id": 4,
                    "created_at": "2021-10-03T23:25:04.526+09:00",
                    "updated_at": "2021-10-03T23:25:04.526+09:00"
                },
                {
                    "id": 7,
                    "sequential_id": 3,
                    "testerId": 9997,
                    "beforeStatus": "issue",
                    "afterStatus": "complete",
                    "reason": "",
                    "team_id": 9999,
                    "project_id": 9999,
                    "testsuite_id": 9991,
                    "testcase_id": 4,
                    "created_at": "2021-10-04T13:00:17.720+09:00",
                    "updated_at": "2021-10-04T13:00:17.720+09:00"
                },
                {
                    "id": 11,
                    "sequential_id": 4,
                    "testerId": 9997,
                    "beforeStatus": "complete",
                    "afterStatus": "complete",
                    "reason": "",
                    "team_id": 9999,
                    "project_id": 9999,
                    "testsuite_id": 9991,
                    "testcase_id": 4,
                    "created_at": "2021-10-12T23:59:28.796+09:00",
                    "updated_at": "2021-10-12T23:59:28.796+09:00"
                }
            ],
            "prerequisites": [],
            "process": [
                {
                    "id": 9,
                    "sequential_id": 1,
                    "contents": "PROCESS",
                    "team_id": 9999,
                    "project_id": 9999,
                    "testsuite_id": 9991,
                    "testcase_id": 4,
                    "created_at": "2021-10-12T23:57:48.502+09:00",
                    "updated_at": "2021-10-12T23:57:48.502+09:00"
                }
            ],
            "expect": []
        },
        {
            "id": 5,
            "title": "DEMO TESTCASE 01",
            "order": 1,
            "sequential_id": 1,
            "status": "complete",
            "creatorId": 9997,
            "testerId": 9997,
            "lastEditorId": 9997,
            "importance": 3,
            "lock": false,
            "team_id": 9999,
            "project_id": 9999,
            "testsuite_id": 9992,
            "created_at": "2021-10-03T22:51:57.280+09:00",
            "updated_at": "2021-10-13T00:04:30.531+09:00",
            "testLogs": [
                {
                    "id": 12,
                    "sequential_id": 1,
                    "testerId": 9997,
                    "beforeStatus": "notRunning",
                    "afterStatus": "complete",
                    "reason": "",
                    "team_id": 9999,
                    "project_id": 9999,
                    "testsuite_id": 9992,
                    "testcase_id": 5,
                    "created_at": "2021-10-13T00:04:30.548+09:00",
                    "updated_at": "2021-10-13T00:04:30.548+09:00"
                }
            ],
            "prerequisites": [],
            "process": [],
            "expect": []
        },
        {
            "id": 6,
            "title": "DEMO TESTCASE 05",
            "order": 5,
            "sequential_id": 5,
            "status": "notRunning",
            "creatorId": 9997,
            "testerId": 9997,
            "lastEditorId": 9997,
            "importance": 3,
            "lock": false,
            "team_id": 9999,
            "project_id": 9999,
            "testsuite_id": 9991,
            "created_at": "2021-10-04T12:37:59.213+09:00",
            "updated_at": "2021-10-12T23:58:02.260+09:00",
            "testLogs": [],
            "prerequisites": [],
            "process": [],
            "expect": []
        },
        {
            "id": 7,
            "title": "DEMO TESTCASE 02",
            "order": 2,
            "sequential_id": 2,
            "status": "complete",
            "creatorId": 9997,
            "testerId": 9997,
            "lastEditorId": 9997,
            "importance": 1,
            "lock": false,
            "team_id": 9999,
            "project_id": 9999,
            "testsuite_id": 9992,
            "created_at": "2021-10-13T00:00:28.209+09:00",
            "updated_at": "2021-10-13T00:04:30.576+09:00",
            "testLogs": [
                {
                    "id": 13,
                    "sequential_id": 1,
                    "testerId": 9997,
                    "beforeStatus": "notRunning",
                    "afterStatus": "complete",
                    "reason": "",
                    "team_id": 9999,
                    "project_id": 9999,
                    "testsuite_id": 9992,
                    "testcase_id": 7,
                    "created_at": "2021-10-13T00:04:30.593+09:00",
                    "updated_at": "2021-10-13T00:04:30.593+09:00"
                }
            ],
            "prerequisites": [
                {
                    "id": 22,
                    "sequential_id": 1,
                    "contents": "PRERERQUISITES01",
                    "team_id": 9999,
                    "project_id": 9999,
                    "testsuite_id": 9992,
                    "testcase_id": 7,
                    "created_at": "2021-10-13T00:00:28.227+09:00",
                    "updated_at": "2021-10-13T00:00:28.227+09:00"
                },
                {
                    "id": 23,
                    "sequential_id": 2,
                    "contents": "PRERERQUISITES02",
                    "team_id": 9999,
                    "project_id": 9999,
                    "testsuite_id": 9992,
                    "testcase_id": 7,
                    "created_at": "2021-10-13T00:00:28.245+09:00",
                    "updated_at": "2021-10-13T00:00:28.245+09:00"
                },
                {
                    "id": 24,
                    "sequential_id": 3,
                    "contents": "PRERERQUISITES03",
                    "team_id": 9999,
                    "project_id": 9999,
                    "testsuite_id": 9992,
                    "testcase_id": 7,
                    "created_at": "2021-10-13T00:00:28.263+09:00",
                    "updated_at": "2021-10-13T00:00:28.263+09:00"
                },
                {
                    "id": 25,
                    "sequential_id": 4,
                    "contents": "PRERERQUISITES04",
                    "team_id": 9999,
                    "project_id": 9999,
                    "testsuite_id": 9992,
                    "testcase_id": 7,
                    "created_at": "2021-10-13T00:00:28.282+09:00",
                    "updated_at": "2021-10-13T00:00:28.282+09:00"
                },
                {
                    "id": 26,
                    "sequential_id": 5,
                    "contents": "PRERERQUISITES05",
                    "team_id": 9999,
                    "project_id": 9999,
                    "testsuite_id": 9992,
                    "testcase_id": 7,
                    "created_at": "2021-10-13T00:00:28.300+09:00",
                    "updated_at": "2021-10-13T00:00:28.300+09:00"
                }
            ],
            "process": [],
            "expect": []
        },
        {
            "id": 8,
            "title": "DEMO TESTCASE 03",
            "order": 3,
            "sequential_id": 3,
            "status": "complete",
            "creatorId": 9997,
            "testerId": 9997,
            "lastEditorId": 9997,
            "importance": 1,
            "lock": false,
            "team_id": 9999,
            "project_id": 9999,
            "testsuite_id": 9992,
            "created_at": "2021-10-13T00:03:10.707+09:00",
            "updated_at": "2021-10-13T00:04:30.625+09:00",
            "testLogs": [
                {
                    "id": 14,
                    "sequential_id": 1,
                    "testerId": 9997,
                    "beforeStatus": "notRunning",
                    "afterStatus": "complete",
                    "reason": "",
                    "team_id": 9999,
                    "project_id": 9999,
                    "testsuite_id": 9992,
                    "testcase_id": 8,
                    "created_at": "2021-10-13T00:04:30.642+09:00",
                    "updated_at": "2021-10-13T00:04:30.642+09:00"
                }
            ],
            "prerequisites": [],
            "process": [
                {
                    "id": 10,
                    "sequential_id": 1,
                    "contents": "PROCESS",
                    "team_id": 9999,
                    "project_id": 9999,
                    "testsuite_id": 9992,
                    "testcase_id": 8,
                    "created_at": "2021-10-13T00:03:10.725+09:00",
                    "updated_at": "2021-10-13T00:03:10.725+09:00"
                }
            ],
            "expect": []
        },
        {
            "id": 9,
            "title": "TESTCASE DEMO 01",
            "order": 1,
            "sequential_id": 1,
            "status": "retest",
            "creatorId": 9997,
            "testerId": 9997,
            "lastEditorId": 9997,
            "importance": 1,
            "lock": false,
            "team_id": 9999,
            "project_id": 9999,
            "testsuite_id": 9993,
            "created_at": "2021-10-15T16:28:06.106+09:00",
            "updated_at": "2021-10-15T16:28:38.498+09:00",
            "testLogs": [
                {
                    "id": 15,
                    "sequential_id": 1,
                    "testerId": 9997,
                    "beforeStatus": "notRunning",
                    "afterStatus": "retest",
                    "reason": "",
                    "team_id": 9999,
                    "project_id": 9999,
                    "testsuite_id": 9993,
                    "testcase_id": 9,
                    "created_at": "2021-10-15T16:28:38.514+09:00",
                    "updated_at": "2021-10-15T16:28:38.514+09:00"
                }
            ],
            "prerequisites": [],
            "process": [],
            "expect": []
        },
        {
            "id": 10,
            "title": "TESTCASE DEMO 02",
            "order": 2,
            "sequential_id": 2,
            "status": "retest",
            "creatorId": 9997,
            "testerId": 9997,
            "lastEditorId": 9997,
            "importance": 1,
            "lock": false,
            "team_id": 9999,
            "project_id": 9999,
            "testsuite_id": 9993,
            "created_at": "2021-10-15T16:28:10.081+09:00",
            "updated_at": "2021-10-15T16:28:38.540+09:00",
            "testLogs": [
                {
                    "id": 16,
                    "sequential_id": 1,
                    "testerId": 9997,
                    "beforeStatus": "notRunning",
                    "afterStatus": "retest",
                    "reason": "",
                    "team_id": 9999,
                    "project_id": 9999,
                    "testsuite_id": 9993,
                    "testcase_id": 10,
                    "created_at": "2021-10-15T16:28:38.556+09:00",
                    "updated_at": "2021-10-15T16:28:38.556+09:00"
                }
            ],
            "prerequisites": [],
            "process": [],
            "expect": []
        },
        {
            "id": 11,
            "title": "TESTCASE DEMO 03",
            "order": 3,
            "sequential_id": 3,
            "status": "retest",
            "creatorId": 9997,
            "testerId": 9997,
            "lastEditorId": 9997,
            "importance": 1,
            "lock": false,
            "team_id": 9999,
            "project_id": 9999,
            "testsuite_id": 9993,
            "created_at": "2021-10-15T16:28:19.526+09:00",
            "updated_at": "2021-10-15T16:28:38.584+09:00",
            "testLogs": [
                {
                    "id": 17,
                    "sequential_id": 1,
                    "testerId": 9997,
                    "beforeStatus": "notRunning",
                    "afterStatus": "retest",
                    "reason": "",
                    "team_id": 9999,
                    "project_id": 9999,
                    "testsuite_id": 9993,
                    "testcase_id": 11,
                    "created_at": "2021-10-15T16:28:38.601+09:00",
                    "updated_at": "2021-10-15T16:28:38.601+09:00"
                }
            ],
            "prerequisites": [],
            "process": [],
            "expect": []
        },
        {
            "id": 12,
            "title": "TESTCASE DEMO 01",
            "order": 1,
            "sequential_id": 1,
            "status": "issue",
            "creatorId": 9997,
            "testerId": 9997,
            "lastEditorId": 9997,
            "importance": 1,
            "lock": false,
            "team_id": 9999,
            "project_id": 9999,
            "testsuite_id": 9994,
            "created_at": "2021-10-15T16:29:01.627+09:00",
            "updated_at": "2021-10-15T16:29:32.186+09:00",
            "testLogs": [
                {
                    "id": 18,
                    "sequential_id": 1,
                    "testerId": 9997,
                    "beforeStatus": "notRunning",
                    "afterStatus": "issue",
                    "reason": "",
                    "team_id": 9999,
                    "project_id": 9999,
                    "testsuite_id": 9994,
                    "testcase_id": 12,
                    "created_at": "2021-10-15T16:29:32.202+09:00",
                    "updated_at": "2021-10-15T16:29:32.202+09:00"
                }
            ],
            "prerequisites": [],
            "process": [],
            "expect": []
        },
        {
            "id": 13,
            "title": "TESTCASE DEMO 02",
            "order": 2,
            "sequential_id": 2,
            "status": "issue",
            "creatorId": 9997,
            "testerId": 9997,
            "lastEditorId": 9997,
            "importance": 1,
            "lock": false,
            "team_id": 9999,
            "project_id": 9999,
            "testsuite_id": 9994,
            "created_at": "2021-10-15T16:29:06.038+09:00",
            "updated_at": "2021-10-15T16:29:32.230+09:00",
            "testLogs": [
                {
                    "id": 19,
                    "sequential_id": 1,
                    "testerId": 9997,
                    "beforeStatus": "notRunning",
                    "afterStatus": "issue",
                    "reason": "",
                    "team_id": 9999,
                    "project_id": 9999,
                    "testsuite_id": 9994,
                    "testcase_id": 13,
                    "created_at": "2021-10-15T16:29:32.247+09:00",
                    "updated_at": "2021-10-15T16:29:32.247+09:00"
                }
            ],
            "prerequisites": [],
            "process": [],
            "expect": []
        },
        {
            "id": 14,
            "title": "TESTCASE DEMO 03",
            "order": 3,
            "sequential_id": 3,
            "status": "issue",
            "creatorId": 9997,
            "testerId": 9997,
            "lastEditorId": 9997,
            "importance": 1,
            "lock": false,
            "team_id": 9999,
            "project_id": 9999,
            "testsuite_id": 9994,
            "created_at": "2021-10-15T16:29:11.623+09:00",
            "updated_at": "2021-10-15T16:29:32.274+09:00",
            "testLogs": [
                {
                    "id": 20,
                    "sequential_id": 1,
                    "testerId": 9997,
                    "beforeStatus": "notRunning",
                    "afterStatus": "issue",
                    "reason": "",
                    "team_id": 9999,
                    "project_id": 9999,
                    "testsuite_id": 9994,
                    "testcase_id": 14,
                    "created_at": "2021-10-15T16:29:32.290+09:00",
                    "updated_at": "2021-10-15T16:29:32.290+09:00"
                }
            ],
            "prerequisites": [],
            "process": [],
            "expect": []
        },
        {
            "id": 15,
            "title": "TESTCASE DEMO 01",
            "order": 1,
            "sequential_id": 1,
            "status": "notRunning",
            "creatorId": 9997,
            "testerId": 9997,
            "lastEditorId": 9997,
            "importance": 1,
            "lock": false,
            "team_id": 9999,
            "project_id": 9999,
            "testsuite_id": 9995,
            "created_at": "2021-10-15T16:29:48.199+09:00",
            "updated_at": "2021-10-15T16:29:48.199+09:00",
            "testLogs": [],
            "prerequisites": [],
            "process": [],
            "expect": []
        },
        {
            "id": 16,
            "title": "TESTCASE DEMO 02",
            "order": 2,
            "sequential_id": 2,
            "status": "notRunning",
            "creatorId": 9997,
            "testerId": 9997,
            "lastEditorId": 9997,
            "importance": 1,
            "lock": false,
            "team_id": 9999,
            "project_id": 9999,
            "testsuite_id": 9995,
            "created_at": "2021-10-15T16:29:55.652+09:00",
            "updated_at": "2021-10-15T16:29:55.652+09:00",
            "testLogs": [],
            "prerequisites": [],
            "process": [],
            "expect": []
        },
        {
            "id": 17,
            "title": "TESTCASE DEMO 03",
            "order": 3,
            "sequential_id": 3,
            "status": "notRunning",
            "creatorId": 9997,
            "testerId": 9997,
            "lastEditorId": 9997,
            "importance": 1,
            "lock": false,
            "team_id": 9999,
            "project_id": 9999,
            "testsuite_id": 9995,
            "created_at": "2021-10-15T16:29:58.588+09:00",
            "updated_at": "2021-10-15T16:29:58.588+09:00",
            "testLogs": [],
            "prerequisites": [],
            "process": [],
            "expect": []
        },
        {
            "id": 18,
            "title": "TESTCASE DEMO 01",
            "order": 1,
            "sequential_id": 1,
            "status": "complete",
            "creatorId": 9997,
            "testerId": 9997,
            "lastEditorId": 9997,
            "importance": 1,
            "lock": false,
            "team_id": 9999,
            "project_id": 9999,
            "testsuite_id": 9996,
            "created_at": "2021-10-15T16:30:13.937+09:00",
            "updated_at": "2021-10-15T16:31:37.110+09:00",
            "testLogs": [
                {
                    "id": 21,
                    "sequential_id": 1,
                    "testerId": 9997,
                    "beforeStatus": "notRunning",
                    "afterStatus": "retest",
                    "reason": "001\nnotRunning -> Retest",
                    "team_id": 9999,
                    "project_id": 9999,
                    "testsuite_id": 9996,
                    "testcase_id": 18,
                    "created_at": "2021-10-15T16:31:00.758+09:00",
                    "updated_at": "2021-10-15T16:31:00.758+09:00"
                },
                {
                    "id": 22,
                    "sequential_id": 2,
                    "testerId": 9997,
                    "beforeStatus": "retest",
                    "afterStatus": "issue",
                    "reason": "002 \nRetest -> Issue",
                    "team_id": 9999,
                    "project_id": 9999,
                    "testsuite_id": 9996,
                    "testcase_id": 18,
                    "created_at": "2021-10-15T16:31:21.168+09:00",
                    "updated_at": "2021-10-15T16:31:21.168+09:00"
                },
                {
                    "id": 23,
                    "sequential_id": 3,
                    "testerId": 9997,
                    "beforeStatus": "issue",
                    "afterStatus": "complete",
                    "reason": "",
                    "team_id": 9999,
                    "project_id": 9999,
                    "testsuite_id": 9996,
                    "testcase_id": 18,
                    "created_at": "2021-10-15T16:31:37.126+09:00",
                    "updated_at": "2021-10-15T16:31:37.126+09:00"
                }
            ],
            "prerequisites": [],
            "process": [],
            "expect": []
        },
        {
            "id": 19,
            "title": "TESTCASE DEMO 01",
            "order": 1,
            "sequential_id": 1,
            "status": "complete",
            "creatorId": 9997,
            "testerId": 9997,
            "lastEditorId": 9997,
            "importance": 1,
            "lock": false,
            "team_id": 9999,
            "project_id": 9999,
            "testsuite_id": 9998,
            "created_at": "2021-10-15T16:31:52.032+09:00",
            "updated_at": "2021-10-15T16:32:59.857+09:00",
            "testLogs": [
                {
                    "id": 24,
                    "sequential_id": 1,
                    "testerId": 9997,
                    "beforeStatus": "notRunning",
                    "afterStatus": "complete",
                    "reason": "",
                    "team_id": 9999,
                    "project_id": 9999,
                    "testsuite_id": 9998,
                    "testcase_id": 19,
                    "created_at": "2021-10-15T16:32:29.398+09:00",
                    "updated_at": "2021-10-15T16:32:29.398+09:00"
                },
                {
                    "id": 25,
                    "sequential_id": 2,
                    "testerId": 9997,
                    "beforeStatus": "complete",
                    "afterStatus": "issue",
                    "reason": "complete -> Issue",
                    "team_id": 9999,
                    "project_id": 9999,
                    "testsuite_id": 9998,
                    "testcase_id": 19,
                    "created_at": "2021-10-15T16:32:47.192+09:00",
                    "updated_at": "2021-10-15T16:32:47.192+09:00"
                },
                {
                    "id": 26,
                    "sequential_id": 3,
                    "testerId": 9997,
                    "beforeStatus": "issue",
                    "afterStatus": "complete",
                    "reason": "",
                    "team_id": 9999,
                    "project_id": 9999,
                    "testsuite_id": 9998,
                    "testcase_id": 19,
                    "created_at": "2021-10-15T16:32:59.875+09:00",
                    "updated_at": "2021-10-15T16:32:59.875+09:00"
                }
            ],
            "prerequisites": [],
            "process": [],
            "expect": []
        },
        {
            "id": 20,
            "title": "TESTCASE DEMO 01",
            "order": 1,
            "sequential_id": 1,
            "status": "notRunning",
            "creatorId": 9997,
            "testerId": 9999,
            "lastEditorId": 9997,
            "importance": 1,
            "lock": false,
            "team_id": 9999,
            "project_id": 9999,
            "testsuite_id": 9998,
            "created_at": "2021-10-15T16:33:10.849+09:00",
            "updated_at": "2021-10-15T16:33:10.849+09:00",
            "testLogs": [],
            "prerequisites": [],
            "process": [],
            "expect": []
        },
        {
            "id": 21,
            "title": "TESTCASE DEMO 01",
            "order": 1,
            "sequential_id": 1,
            "status": "notRunning",
            "creatorId": 9997,
            "testerId": 9998,
            "lastEditorId": 9997,
            "importance": 1,
            "lock": false,
            "team_id": 9999,
            "project_id": 9999,
            "testsuite_id": 10000,
            "created_at": "2021-10-15T16:33:20.917+09:00",
            "updated_at": "2021-10-15T16:33:20.917+09:00",
            "testLogs": [],
            "prerequisites": [],
            "process": [],
            "expect": []
        }
    ]
}